azure_transcription_client/__init__.py
azure_transcription_client/api_client.py
azure_transcription_client/configuration.py
azure_transcription_client/rest.py
azure_transcription_client/api/__init__.py
azure_transcription_client/api/default_api.py
azure_transcription_client/models/__init__.py
azure_transcription_client/models/api_speechtotext_v30_datasets_locales_get200_application_json_response.py
azure_transcription_client/models/api_speechtotext_v30_endpoints_locales_get200_application_json_response.py
azure_transcription_client/models/api_speechtotext_v30_evaluations_locales_get200_application_json_response.py
azure_transcription_client/models/api_speechtotext_v30_models_locales_get200_application_json_response.py
azure_transcription_client/models/api_speechtotext_v30_projects_locales_get200_application_json_response.py
azure_transcription_client/models/api_speechtotext_v30_transcriptions_locales_get200_application_json_response.py
azure_transcription_client/models/component.py
azure_transcription_client/models/dataset.py
azure_transcription_client/models/dataset_properties.py
azure_transcription_client/models/dataset_update.py
azure_transcription_client/models/endpoint.py
azure_transcription_client/models/endpoint_links.py
azure_transcription_client/models/endpoint_properties.py
azure_transcription_client/models/endpoint_properties_update.py
azure_transcription_client/models/endpoint_update.py
azure_transcription_client/models/entity_error.py
azure_transcription_client/models/entity_reference.py
azure_transcription_client/models/error.py
azure_transcription_client/models/error_content.py
azure_transcription_client/models/error_detail.py
azure_transcription_client/models/evaluation.py
azure_transcription_client/models/evaluation_properties.py
azure_transcription_client/models/evaluation_update.py
azure_transcription_client/models/file.py
azure_transcription_client/models/file_links.py
azure_transcription_client/models/file_properties.py
azure_transcription_client-0.1.0.dist-info/METADATA
azure_transcription_client-0.1.0.dist-info/WHEEL
azure_transcription_client-0.1.0.dist-info/top_level.txt
azure_transcription_client-0.1.0.dist-info/RECORD
