Metadata-Version: 2.1
Name: azure-transcription-client
Version: 0.1.0
Summary: Speech to Text API v3.0
Author-email: Vito Stamatti <vitostamatti@gmail.com>
Project-URL: Homepage, https://github.com/vitostamatti/azure-transcription-python-client
Project-URL: Source code, https://github.com/vitostamatti/azure-transcription-python-client
Requires-Python: >=3.10
Requires-Dist: certifi >=2017.4.17
Requires-Dist: python-dateutil >=2.1
Requires-Dist: six >=1.10
Requires-Dist: urllib3 >=1.23
